AUTHORS
LICENSE
MANIFEST.in
README.md
setup.py
django_tokenapi2.egg-info/PKG-INFO
django_tokenapi2.egg-info/SOURCES.txt
django_tokenapi2.egg-info/dependency_links.txt
django_tokenapi2.egg-info/requires.txt
django_tokenapi2.egg-info/top_level.txt
tokenapi/__init__.py
tokenapi/backends.py
tokenapi/decorators.py
tokenapi/http.py
tokenapi/models.py
tokenapi/tokens.py
tokenapi/urls.py
tokenapi/views.py