Metadata-Version: 2.1
Name: django-tokenapi2
Version: 2.1
Summary: A fork from Julian Pulgarin django-tokenapi with Django 4+ support.
Home-page: https://github.com/Starou/django-tokenapi
Author: Stanislas Guerra
Author-email: stan@slashdev.fr
License: Apache License, Version 2.0
Platform: UNKNOWN
Classifier: Programming Language :: Python :: 3
License-File: LICENSE
License-File: AUTHORS
